setup.py
myadipkg/__init__.py
myadipkg/calculator.py
somadipkg.egg-info/PKG-INFO
somadipkg.egg-info/SOURCES.txt
somadipkg.egg-info/dependency_links.txt
somadipkg.egg-info/top_level.txt