Metadata-Version: 2.1
Name: somadipkg
Version: 0.0.1
Summary: ADI python package module
Home-page: https://github.com/hkshitesh/mydemopackage
Author: Somali
Author-email: somalibhosale7@gmail.com
Classifier: Programming Language :: Python :: 3
Classifier: Operating System :: OS Independent
